pytesycloud/__init__.py
pyTesyCloud-0.0.4.dist-info/METADATA
pyTesyCloud-0.0.4.dist-info/WHEEL
pyTesyCloud-0.0.4.dist-info/top_level.txt
pyTesyCloud-0.0.4.dist-info/RECORD
