Metadata-Version: 2.1
Name: pyTesyCloud
Version: 0.0.4
Summary: Library for Tesy smart home devices. Based on StyraHem/pyTesy
Home-page: https://github.com/strainu/pyTesyCloud
Author: Strainu
Author-email: pypi@strainu.ro
Classifier: Programming Language :: Python :: 3
Classifier: License :: OSI Approved :: MIT License
Classifier: Operating System :: OS Independent
